./.gitignore
./.python-version
./CONTRIBUTING.md
./Dockerfile
./LICENSE
./PKG-INFO
./README.md
./ROADMAP.md
./SECURITY.md
./docs_updater.py
./laravel_docs_server.py
./pyproject.toml
./requirements-dev.txt
./shutdown_handler.py
./smithery.yaml
./uv.lock
./.github/ISSUE_TEMPLATE/bug_report.md
./.github/ISSUE_TEMPLATE/feature_request.md
./.github/workflows/ci.yaml
./.github/workflows/docs-update.yaml
./.github/workflows/release.yaml
./docs/.metadata/sync_info.json
./docs/10.x/artisan.md
./docs/10.x/authentication.md
./docs/10.x/authorization.md
./docs/10.x/billing.md
./docs/10.x/blade.md
./docs/10.x/broadcasting.md
./docs/10.x/cache.md
./docs/10.x/cashier-paddle.md
./docs/10.x/collections.md
./docs/10.x/configuration.md
./docs/10.x/console-tests.md
./docs/10.x/container.md
./docs/10.x/contracts.md
./docs/10.x/contributions.md
./docs/10.x/controllers.md
./docs/10.x/csrf.md
./docs/10.x/database-testing.md
./docs/10.x/database.md
./docs/10.x/deployment.md
./docs/10.x/documentation.md
./docs/10.x/dusk.md
./docs/10.x/eloquent-collections.md
./docs/10.x/eloquent-factories.md
./docs/10.x/eloquent-mutators.md
./docs/10.x/eloquent-relationships.md
./docs/10.x/eloquent-resources.md
./docs/10.x/eloquent-serialization.md
./docs/10.x/eloquent.md
./docs/10.x/encryption.md
./docs/10.x/envoy.md
./docs/10.x/errors.md
./docs/10.x/events.md
./docs/10.x/facades.md
./docs/10.x/filesystem.md
./docs/10.x/folio.md
./docs/10.x/fortify.md
./docs/10.x/frontend.md
./docs/10.x/hashing.md
./docs/10.x/helpers.md
./docs/10.x/homestead.md
./docs/10.x/horizon.md
./docs/10.x/http-client.md
./docs/10.x/http-tests.md
./docs/10.x/installation.md
./docs/10.x/license.md
./docs/10.x/lifecycle.md
./docs/10.x/localization.md
./docs/10.x/logging.md
./docs/10.x/mail.md
./docs/10.x/middleware.md
./docs/10.x/migrations.md
./docs/10.x/mix.md
./docs/10.x/mocking.md
./docs/10.x/notifications.md
./docs/10.x/octane.md
./docs/10.x/packages.md
./docs/10.x/pagination.md
./docs/10.x/passport.md
./docs/10.x/passwords.md
laravel_docs_mcp-0.3.1.dist-info/METADATA
laravel_docs_mcp-0.3.1.dist-info/WHEEL
laravel_docs_mcp-0.3.1.dist-info/licenses/LICENSE
laravel_docs_mcp-0.3.1.dist-info/RECORD
