Metadata-Version: 2.4
Name: laravel-docs-mcp
Version: 0.3.1
Summary: Model Context Protocol (MCP) server for accessing and searching Laravel 12 documentation. Enables AI assistants and tools to query Laravel docs through a standardized interface.
Project-URL: Homepage, https://github.com/brianirish/laravel-docs-mcp
Project-URL: Bug Tracker, https://github.com/brianirish/laravel-docs-mcp/issues
Author-email: Brian Irish <brian.irish@superorbital.io>
License: MIT
License-File: LICENSE
Keywords: ai,claude,documentation,fastmcp,laravel,mcp
Classifier: Development Status :: 4 - Beta
Classifier: Intended Audience :: Developers
Classifier: License :: OSI Approved :: MIT License
Classifier: Programming Language :: Python :: 3
Classifier: Programming Language :: Python :: 3.12
Classifier: Topic :: Software Development :: Documentation
Requires-Python: >=3.12
Requires-Dist: fastmcp>=2.2.0
Requires-Dist: mcp[cli,client]>=1.6.0
